Inputron/__init__.py
Inputron/main.py
Inputron-1.2.2.dist-info/LICENSE
Inputron-1.2.2.dist-info/METADATA
Inputron-1.2.2.dist-info/WHEEL
Inputron-1.2.2.dist-info/top_level.txt
Inputron-1.2.2.dist-info/RECORD
