Metadata-Version: 2.1
Name: Inputron
Version: 1.2.2
Summary: Control your Outputs as if they were your
Home-page: https://github.com/G4brielXavier/Inputron.git
Author: dotxavierket
Author-email: xavier.gabriel3728@gmail.com
Classifier: Programming Language :: Python :: 3
Classifier: License :: OSI Approved :: MIT License
Requires-Python: >=3.6
License-File: LICENSE
